job_queue_processor/__init__.py
job_queue_processor/processor.py
job_queue_processor/queue.py
job_queue_processor/cli/__init__.py
job_queue_processor/cli/monitor.py
job_queue_processor/cli/process.py
job_queue_processor/cli/submit.py
job_queue_processor-0.1.0.dist-info/METADATA
job_queue_processor-0.1.0.dist-info/WHEEL
job_queue_processor-0.1.0.dist-info/entry_points.txt
job_queue_processor-0.1.0.dist-info/licenses/LICENSE
job_queue_processor-0.1.0.dist-info/RECORD
