Metadata-Version: 2.4
Name: job-queue-processor
Version: 0.1.0
Summary: Simple, extensible job queue processor with MongoDB backend
Project-URL: Homepage, https://github.com/miroblog/job-queue-processor
Project-URL: Repository, https://github.com/miroblog/job-queue-processor
Project-URL: Documentation, https://github.com/miroblog/job-queue-processor#readme
Project-URL: Bug Tracker, https://github.com/miroblog/job-queue-processor/issues
Author-email: Your Name <your.email@example.com>
License: MIT
License-File: LICENSE
Keywords: async,job,mongodb,processor,queue,worker
Classifier: Development Status :: 4 - Beta
Classifier: Intended Audience :: Developers
Classifier: License :: OSI Approved :: MIT License
Classifier: Programming Language :: Python :: 3
Classifier: Programming Language :: Python :: 3.8
Classifier: Programming Language :: Python :: 3.9
Classifier: Programming Language :: Python :: 3.10
Classifier: Programming Language :: Python :: 3.11
Classifier: Programming Language :: Python :: 3.12
Classifier: Topic :: Software Development :: Libraries :: Python Modules
Classifier: Topic :: System :: Distributed Computing
Requires-Python: >=3.8
Requires-Dist: pymongo>=4.0.0
Requires-Dist: python-dotenv>=1.0.0
Provides-Extra: dev
Requires-Dist: black>=23.0; extra == 'dev'
Requires-Dist: pytest-cov>=4.0; extra == 'dev'
Requires-Dist: pytest>=7.0; extra == 'dev'
Requires-Dist: ruff>=0.1.0; extra == 'dev'
